AUTHORS
BUGS.md
CHANGES.rst
LICENSE
MANIFEST.in
README.rst
TODO.md
setup.py
docs/Makefile
docs/api.rst
docs/api_TODO_MODULE_NAME.rst
docs/conf.py
docs/developer.rst
docs/index.rst
docs/init_sphinx.sh
docs/intro.rst
docs/make.bat
rpsl/__init__.py
rpsl/temperature.py
rpsl.egg-info/PKG-INFO
rpsl.egg-info/SOURCES.txt
rpsl.egg-info/dependency_links.txt
rpsl.egg-info/entry_points.txt
rpsl.egg-info/top_level.txt