Metadata-Version: 1.2
Name: rpsl
Version: 0.1.dev1
Summary: A Raspberry Pi Sensor Library
Home-page: http://www.jdhp.org/software_en.html#rpsl
Author: Jérémie DECOCK
Author-email: jd.jdhp@gmail.com
Maintainer: Jérémie DECOCK
Maintainer-email: jd.jdhp@gmail.com
License: UNKNOWN
Download-URL: http://www.jdhp.org/software_en.html#rpsl
Keywords: rpsl
Platform: UNKNOWN
Classifier: Development Status :: 4 - Beta
Classifier: Intended Audience :: Developers
Classifier: License :: OSI Approved :: MIT License
Classifier: Natural Language :: English
Classifier: Operating System :: OS Independent
Classifier: Programming Language :: Python :: 3
Classifier: Topic :: Software Development :: Libraries
Classifier: Topic :: Software Development :: Libraries :: Python Modules
Classifier: Topic :: Software Development :: Libraries :: Application Frameworks
